<?xml version="1.0" encoding="utf-8" ?>
<HoNBuildPlanner>
  <Hero>
    <Name>Glacius</Name>
    <PrimaryAttribute>Intelligence</PrimaryAttribute>
    <InitialHP>150</InitialHP>
    <InitialHPRegen>0.25</InitialHPRegen>
    <InitialMana>0</InitialMana>
    <InitialManaRegen>0.01</InitialManaRegen>
    <InitialAttirbutes>
      <Strength>16</Strength>
      <Agility>16</Agility>
      <Intelligence>21</Intelligence>
    </InitialAttirbutes>
    <MovementSpeed>280</MovementSpeed>
    <PerLevel>
      <Strength>1.7</Strength>
      <Agility>1.6</Agility>
      <Intelligence>2.9</Intelligence>      
    </PerLevel>
    <Armor>-1.0</Armor>
    <MagicArmor>5.5</MagicArmor>
    <AttackType>Ranged</AttackType>
    <MinDamage>17</MinDamage>
    <MaxDamage>23</MaxDamage>
    <Range>600</Range>
    <BAT>1.7</BAT>
    <Skills>
      <Skill>
        <Name>Tundra Blast</Name>
        <Lore>Glacius assaults a group of enemies with an explosion of ice. All enemies hit by the explosion are damaged and have their movement and attack speed slowed.</Lore>
        <normalimage>tundrablast</normalimage>
      </Skill>
      <Skill>
        <Name>Ice Imprisonment</Name>
        <Lore>Glacius encases a target enemy unit in ice. The target unit is frozen solid, rendering it unable to move or attack. The target unit takes damage over time while frozen.</Lore>
        <normalimage>iceimprisonment</normalimage>
      </Skill>
      <Skill>
        <Name>Chilling Presence</Name>
        <Lore>Glacius helps his allies remain cool in the face of danger, giving them a clear and calm mind. Increases Mana regeneration to all allied Heroes no matter where they are on the map.</Lore>
        <normalimage>chillingpresence</normalimage>
      </Skill>
      <Skill>
        <Name>Glacial Downpour</Name>
        <Lore>Glacius showers the area around him with shards of ice. The shards will randomly strike around Glacius, slowing the attack and movement speed of nearby enemies and dealing intense damage to them.</Lore>
        <normalimage>glacialdownpour</normalimage>
      </Skill>
    </Skills>
    <portrait>glacius.jpeg</portrait>
  </Hero>
  
  <Hero>
    <Name>Accursed</Name>
    <PrimaryAttribute>Strength</PrimaryAttribute>
    <InitialHP>150</InitialHP>
    <InitialHPRegen>0.25</InitialHPRegen>
    <InitialMana>0</InitialMana>
    <InitialManaRegen>0.01</InitialManaRegen>
    <InitialAttirbutes>
      <Strength>23</Strength>
      <Agility>17</Agility>
      <Intelligence>21</Intelligence>
    </InitialAttirbutes>
    <MovementSpeed>300</MovementSpeed>
    <PerLevel>
      <Strength>2.7</Strength>
      <Agility>1.5</Agility>
      <Intelligence>2.0</Intelligence>
    </PerLevel>
    <Armor>2.0</Armor>
    <MagicArmor>5.0</MagicArmor>
    <AttackType>Melee</AttackType>
    <MinDamage>31</MinDamage>
    <MaxDamage>33</MaxDamage>
    <Range>110</Range>
    <BAT>1.7</BAT>
    <Skills>
      <Skill>
        <Name>Cauterize</Name>
        <Lore>At the cost of some of his own Health, Accursed bursts the air around a target, dealing damage to them if they are an enemy or healing them if they are an ally.</Lore>
        <normalimage>cauterize</normalimage>
      </Skill>
      <Skill>
        <Name>Fire Shield</Name>
        <Lore>Accursed covers a friendly unit in a shield of flames protecting them from damage and removing harmful effects. If the shield is damaged to its breaking point, it will explode, dealing Magical damage to nearby enemies equal to that of the damage absorbed.</Lore>
        <normalimage>fireshield</normalimage>
      </Skill>
      <Skill>
        <Name>Sear</Name>
        <Lore>Causes Accursed's attacks to sear his target, slowing their movement speed. Any ally that attacks the affected unit will be buffed with increased attack speed and movement speed.</Lore>
        <normalimage>sear</normalimage>
      </Skill>
      <Skill>
        <Name>Flame Consumption</Name>
        <Lore>Accursed summons a powerful fire tornado around himself which, when fueled with damage, causes him to regain his life. When not in cooldown, this ability automatically activates when The Accursed drops below 400 Health.</Lore>
        <normalimage>flameconsumption</normalimage>
      </Skill>
    </Skills>
    <portrait>accursed.jpeg</portrait>
  </Hero>

  <Hero>
    <Name>Devourer</Name>
    <PrimaryAttribute>Strength</PrimaryAttribute>
    <InitialHP>150</InitialHP>
    <InitialHPRegen>0.25</InitialHPRegen>
    <InitialMana>0</InitialMana>
    <InitialManaRegen>0.01</InitialManaRegen>
    <InitialAttirbutes>
      <Strength>25</Strength>
      <Agility>14</Agility>
      <Intelligence>14</Intelligence>
    </InitialAttirbutes>
    <MovementSpeed>285</MovementSpeed>
    <PerLevel>
      <Strength>3.2</Strength>
      <Agility>1.5</Agility>
      <Intelligence>1.5</Intelligence>
    </PerLevel>
    <Armor>0.0</Armor>
    <MagicArmor>5.5</MagicArmor>
    <AttackType>Melee</AttackType>
    <MinDamage>27</MinDamage>
    <MaxDamage>33</MaxDamage>
    <Range>128</Range>
    <BAT>1.7</BAT>
    <Skills>
      <Skill>
        <Name>Guttling Hook</Name>
        <Lore>The Devourer launches his Guttling Hook at a target unit or location. The first targetable unit that touches the hook will be dragged back to the Devourer.</Lore>
        <normalimage>guttlinghook</normalimage>
      </Skill>
      <Skill>
        <Name>Decay</Name>
        <Lore>The Devourer allows himself to decay, draining his Health over time and releasing poisonous gasses that both damage and slow nearby enemy units.</Lore>
        <normalimage>decay</normalimage>
      </Skill>
      <Skill>
        <Name>Cadaver Armor</Name>
        <Lore>This grotesque armor increases the Devourer's Magic Armor and permanently adds {0.9,1.2,1.5,1.8} strength for each hero kill and {0.03,0.06,0.09,0.12} strength for each creep kill he makes.</Lore>
        <normalimage>cadaverarmor</normalimage>
      </Skill>
      <Skill>
        <Name>Devour</Name>
        <Lore>The Devourer grabs a target enemy and feasts on their flesh, dealing massive damage for every second he feeds.</Lore>
        <normalimage>devour</normalimage>
      </Skill>
    </Skills>
    <portrait>devourer.jpeg</portrait>
  </Hero>

  <Hero>
    <Name>Electrician</Name>
    <PrimaryAttribute>Strength</PrimaryAttribute>
    <InitialHP>150</InitialHP>
    <InitialHPRegen>0.25</InitialHPRegen>
    <InitialMana>0</InitialMana>
    <InitialManaRegen>0.01</InitialManaRegen>
    <InitialAttirbutes>
      <Strength>23</Strength>
      <Agility>15</Agility>
      <Intelligence>25</Intelligence>
    </InitialAttirbutes>
    <MovementSpeed>300</MovementSpeed>
    <PerLevel>
      <Strength>2.4</Strength>
      <Agility>2.0</Agility>
      <Intelligence>1.3</Intelligence>
    </PerLevel>
    <Armor>0.0</Armor>
    <MagicArmor>5.5</MagicArmor>
    <AttackType>Melee</AttackType>
    <MinDamage>30</MinDamage>
    <MaxDamage>38</MaxDamage>
    <Range>100</Range>
    <BAT>1.7</BAT>
    <Skills>
      <Skill>
        <Name>Static Grip</Name>
        <Lore>The Electrician binds a target in a static grip, preventing them from casting spells, moving, attacking, or using items for a short time. The Electrician is dragged slowly toward the target.</Lore>
        <normalimage>staticgrip</normalimage>
      </Skill>
      <Skill>
        <Name>Electric Shield</Name>
        <Lore>The electrician uses electricity to create a shield around himself. The shield will negate a portion of incoming damage at the cost of Electrician's Mana.</Lore>
        <normalimage>electricshield</normalimage>
      </Skill>
      <Skill>
        <Name>Energy Absorption</Name>
        <Lore>The Electrician discharges energy around him. Nearby enemies are damaged and have their Mana drained. For each enemy with Mana drained, the Electrician absorbs some Mana, gets a boost to his Magic Armor and a boost to Physical Armor.</Lore>
        <normalimage>energyabsorption</normalimage>
      </Skill>
      <Skill>
        <Name>Cleansing Shock</Name>
        <Lore>Electrician shocks a target unit, removing debuffs and increasing movement speed if the target is an ally, or removing buffs and decreasing movement speed if target is an enemy.</Lore>
        <normalimage>cleansingshock</normalimage>
      </Skill>
    </Skills>
    <portrait>electrician.jpeg</portrait>
  </Hero>

  <Hero>
    <Name>Kraken</Name>
    <PrimaryAttribute>Strength</PrimaryAttribute>
    <InitialHP>150</InitialHP>
    <InitialHPRegen>0.25</InitialHPRegen>
    <InitialMana>0</InitialMana>
    <InitialManaRegen>0.01</InitialManaRegen>
    <InitialAttirbutes>
      <Strength>22</Strength>
      <Agility>15</Agility>
      <Intelligence>16</Intelligence>
    </InitialAttirbutes>
    <MovementSpeed>310</MovementSpeed>
    <PerLevel>
      <Strength>3</Strength>
      <Agility>1.5</Agility>
      <Intelligence>1.7</Intelligence>
    </PerLevel>
    <Armor>1.0</Armor>
    <MagicArmor>5.5</MagicArmor>
    <AttackType>Melee</AttackType>
    <MinDamage>25</MinDamage>
    <MaxDamage>31</MaxDamage>
    <Range>125</Range>
    <BAT>1.7</BAT>
    <Skills>
      <Skill>
        <Name>Splash</Name>
        <Lore>When attacking, Kraken unleashes a mighty attack that damages nearby enemies.</Lore>
        <normalimage>splash</normalimage>
      </Skill>
      <Skill>
        <Name>Tsunami Charge</Name>
        <Lore>Kraken charges toward a target location with great strength and speed, damaging and knocking aside enemies in his path.</Lore>
        <normalimage>tsunamicharge</normalimage>
      </Skill>
      <Skill>
        <Name>Tidal Pull</Name>
        <Lore>Kraken's presence slows nearby enemies with a continuous tidal pull.</Lore>
        <normalimage>tidalpull</normalimage>
      </Skill>
      <Skill>
        <Name>Whirlpool</Name>
        <Lore>Kraken forms two connected whirlpools, one at a target location and one around himself. After a short time, the whirlpool near Kraken sucks everyone in and spits them out at the targeted location. Enemies are damaged in the process.</Lore>
        <normalimage>whirlpool</normalimage>
      </Skill>
    </Skills>
    <portrait>kraken.jpeg</portrait>
  </Hero>
</HoNBuildPlanner>
